<CIVIL-CODE>
    <INFORMATION>
        <NAME>CIVIL CODE</NAME>
        <YEAR>2015</YEAR>
        <CHAPTER>16</CHAPTER>
        <LINK>https://thuvienphapluat.vn/van-ban/Quyen-dan-su/Bo-luat-dan-su-2015-296215.aspx</LINK>
    </INFORMATION>
    
    <CONVERSATION id='1' article="466">
        <QUESTIONS>
            <QUESTION>Khi vay có lãi mà đến hạn không trả thì phải trả lãi bao nhiêu?</QUESTION>
        </QUESTIONS>
        <ANSWERS>
            <ANSWER>Trước tiên, việc con trai của bận vay tiền là thỏa thuận vay tài sản, quan hệ dân sự giữa hai cá nhân. Và theo như thông tin bạn cung cấp thì con trai bạn hiện đã là người thành niên (trên 18 tuổi), có năng lực hành vi dân sự đầy đủ nên theo quy định tại Bộ Luật dân sự 2015 thì con trai bạn tự chịu trách nhiệm về việc thực hiện nghĩa vụ dân sự phát sinh từ các giao dịch do mình xác lập, cụ thể là tự chịu trách nhiệm trả nợ cho bên cho vay theo thỏa thuận của các bên.&#xA;Theo đó, bạn không có nghĩa vụ trả tiền nợ thay con trai của mình và hành vi của bên đòi nợ là hoàn toàn vi phạm pháp luật.&#xA;Để bảo vệ bản thân và gia đình,bạn nên thực hiện các bước như sau:&#xA;Bước 01: Thông báo rõ ràng với bên cho vay về việc con bạn không còn ở nhà bạn và đề nghị không được làm phiền đến cuộc sống của bạn và gia đình.&#xA;Bước 02: Nếu bên cho vay vẫn tiếp tục đến làm phiền, gây rối, chửi bới, gây sức ép, đe dọa làm ảnh hưởng đến cuộc sống thì bạn cần ghi lại bằng chứng (hình ảnh, video, ghi âm…) hành vi vi phạm.&#xA;Bước 03: Gọi báo ngay Công an phường/xã nơi bạn đang sinh sống để đề nghị cơ quan công an can thiệp giải quyết và lập biên bản sự việc.&#xA;Trường hợp các đối tượng trên bỏ đi khi biết bạn báo công an thì khi công an đến làm việc, bạn vẫn nên trình báo toàn bộ sự việc, cung cấp các bằng chứng (hình ảnh, video, ghi âm…) hành vi vi phạm và đề nghị cơ quan công an lập văn bản trình báo hoặc đơn tố giác tội phạm để tiếp nhận và xử lý theo quy định pháp luật.&#xA;Bước 04: Nếu bạn đã có trình báo và gửi đầy đủ chứng cứ về hành vi vi phạm của bên cho vay đến Công an phường yêu cầu giải quyết nhưng không được giải quyết hoặc giải quyết không thỏa đáng thì bạn có thể khiếu nại hoặc gửi đơn tố cáo tội phạm gửi đến Công an cấp cao hơn để yêu cầu giải quyết.&#xA;Ngoài ra, để đảm bảo cuộc sống được tiếp diễn bình thường, bạn nên lắp đặt một số camera tại các vị trí trong và trước nhà nhằm ghi lại hình ảnh bên cho vay gây rối, gây áp lực hoặc ghi lại những hành vi vi phạm pháp luật khác làm ảnh hưởng để sau này có căn cứ tố cáo.</ANSWER>
        </ANSWERS>
    </CONVERSATION>

    <CONVERSATION id='2' article="439">
        <QUESTIONS>
            <QUESTION>Mua xe máy nhưng người bán giao xe không đúng màu sắc đã thoả thuận thì xử lý thế nào?</QUESTION>
        </QUESTIONS>
        <ANSWERS>
            <ANSWER>Khi bên bán giao xe không đúng màu sắc đã thoả thuận trong hợp đồng thì sẽ có 4 hướng xử lý sau: Nhận xe và thanh toán theo thỏa thuận; yêu cầu giao xe đúng và bồi thường; hủy hợp đồng mua bán và yêu cầu bồi thường hoặc khởi kiện ra toà án.</ANSWER>
        </ANSWERS>
    </CONVERSATION>

    <CONVERSATION id='3' article="466">
        <QUESTIONS>
            <QUESTION>Bị khủng bố đòi nợ dù không vay tiền, phải làm sao?</QUESTION>
        </QUESTIONS>
        <ANSWERS>
            <ANSWER>Pháp luật quy định bên vay tài sản là đối tượng phải thực hiện nghĩa vụ trả nợ, không quy định trường hợp không trả nợ hoặc không có khả năng trả nợ nữa thì người thân phải trả thay, trả dùm. Do đó, nếu bạn không vay tiền thì không có nghĩa vụ phải trả tiền vay này.&#xA;Cho nên, với hành vi khủng bố tinh thần, đe dọa đòi nợ như chửi bới, tạt sơn, bắt loa để đòi nợ,...v.v thì bên đòi nợ đã vi phạm pháp luật, đối với hành vi này, họ sẽ bị xử phạt hành chính, nếu hậu quả thiệt hại nặng nề, họ sẽ bị truy cứu trách nhiệm hình sự.&#xA;Do đó, khi gặp trường hợp này, nếu bạn cảm thấy rằng sự việc đang diễn ra có thể gây nguy hiểm, đe dọa đến tính mạng và sức khỏe của bản thân cũng như các thành viên trong gia đình, bạn cần trình báo sự việc đến công an xã, phường nởi xảy ra sự việc ngay lập tức.&#xA;Việc này không chỉ giúp bảo vệ quyền lợi của bạn mà còn tạo điều kiện cho cơ quan chức năng can thiệp kịp thời, đảm bảo an ninh và trật tự tại khu vực cư trú của bạn.</ANSWER>
        </ANSWERS>
    </CONVERSATION>

    <CONVERSATION id='4' article="468">
        <QUESTIONS>
            <QUESTION>Công ty được cho vay vốn với lãi suất tối đa là bao nhiêu?</QUESTION>
        </QUESTIONS>
        <ANSWERS>
            <ANSWER>Công ty được cho vay với lãi suất tối đa là 20%/năm của khoản tiền vay.</ANSWER>
        </ANSWERS>
    </CONVERSATION>

    <CONVERSATION id='5' article="468">
        <QUESTIONS>
            <QUESTION>Lãi suất cho vay tối đa là bao nhiêu?</QUESTION>
        </QUESTIONS>
        <ANSWERS>
            <ANSWER>Mức lãi suất cho vay tối đa được tính là 20%/năm, nếu hai bên thỏa thuận mức lãi suất cao hơn mức giới hạn này thì phần vượt quá sẽ không có hiệu lực.</ANSWER>
        </ANSWERS>
    </CONVERSATION>

    <CONVERSATION id='6' article="472">
        <QUESTIONS>
            <QUESTION>Cho thuê chung cư có cần sự đồng ý của ban quản lý chung cư không?</QUESTION>
        </QUESTIONS>
        <ANSWERS>
            <ANSWER>Trường hợp cho thuê chung cư thì người thuê và người cho thuê không phải xin phép ban quản lý chung cư mà hoàn toàn có quyền được cho thuê theo thoả thuận của các bên.</ANSWER>
        </ANSWERS>
    </CONVERSATION>

    <CONVERSATION id='7' article="463">
        <QUESTIONS>
            <QUESTION>Bên cho vay nặng lãi bị bắt thì bên vay tiền có phải trả nợ không?</QUESTION>
        </QUESTIONS>
        <ANSWERS>
            <ANSWER>Bên cho vay nặng lãi dù cho đang bị bắt, đang chấp hành án phạt tù thì cũng không bị tước quyền công dân, theo đó bên cho vay vẫn có quyền được bên có nghĩa vụ thực hiện hợp đồng, tức bên vay vẫn phải trả nợ theo đúng như đã giao kết trong hợp đồng vay.</ANSWER>
        </ANSWERS>
    </CONVERSATION>

    <CONVERSATION id='8' article="468">
        <QUESTIONS>
            <QUESTION>Khoản lãi vay vượt quá quy định pháp luật thì bên vay tiền có phải trả không?</QUESTION>
        </QUESTIONS>
        <ANSWERS>
            <ANSWER>Nếu cho vay nặng lãi thì bên vay sẽ không phải trả số tiền lãi vượt quá mức lãi suất theo quy định (quá 20%/năm của khoản tiền vay) nhưng vẫn phải trả đầy đủ số tiền đã mượn và phần lãi nằm trong quy định.</ANSWER>
        </ANSWERS>
    </CONVERSATION>

    <CONVERSATION id='9'>
        <QUESTIONS>
            <QUESTION>Cho vay nặng lãi từ bao nhiêu sẽ bị bắt?</QUESTION>
        </QUESTIONS>
        <ANSWERS>
            <ANSWER>Nếu cho vay với mức lãi suất 100%/năm của khoản tiền vay hoặc số tiền lãi vượt quá 20%/năm của khoảng tiền vay từ 30 triệu đồng trở lên thì sẽ bị bắt</ANSWER>
        </ANSWERS>
    </CONVERSATION>

    <CONVERSATION id='10' article="472,475">
        <QUESTIONS>
            <QUESTION>Cho thuê lại một góc nhỏ của mặt bằng đang thuê có cần chủ nhà đồng ý không?</QUESTION>
        </QUESTIONS>
        <ANSWERS>
            <ANSWER>Việc cho thuê lại đối với mặt bằng đang thuê theo quy định pháp luật thì phải mặc nhiên được chủ nhà đồng ý, trừ khi trong hợp đồng có thỏa thuận bên thuê được phép cho thuê lại một phần hoặc toàn bộ mặt bằng.</ANSWER>
        </ANSWERS>
    </CONVERSATION>

    <CONVERSATION id='11' article="445">
        <QUESTIONS>
            <QUESTION>Hàng hóa sau khi mua đã hết sản xuất nếu bị hư hỏng có được bảo hành?</QUESTION>
        </QUESTIONS>
        <ANSWERS>
            <ANSWER>Nếu hàng hóa đã hết sản xuất thì lấy vật khác thay thế, giảm giá và bồi thường thiệt hại, trừ trường hợp có thỏa thuận khác.</ANSWER>
        </ANSWERS>
    </CONVERSATION>

    <CONVERSATION id='12' article="472">
        <QUESTIONS>
            <QUESTION>Hợp đồng thuê nhà là gì?</QUESTION>
        </QUESTIONS>
        <ANSWERS>
            <ANSWER>Hợp đồng thuê nhà là một thỏa thuận pháp lý giữa chủ nhà và người thuê nhà. Trong hợp đồng này, chủ nhà đồng ý cho người thuê sử dụng tài sản của mình, thường là một căn nhà hoặc căn hộ trong một khoảng thời gian nhất định với điều kiện người thuê phải trả tiền thuê nhà theo đúng thỏa thuận.</ANSWER>
        </ANSWERS>
    </CONVERSATION>

    <CONVERSATION id='13' article="459">
        <QUESTIONS>
            <QUESTION>Quyền sử dụng đất đã sang tên cho con thì có đòi lại được không?</QUESTION>
        </QUESTIONS>
        <ANSWERS>
            <ANSWER clause='1,2'>Trong trường hợp này cha mẹ đã tặng cho tài sản cho con rồi và đã thực hiện thủ tục sang tên tài sản rồi. Do đó, lúc này quyền sử dụng đất và tài sản trên đất này của người con đã được xác lập. Người con là sẽ là chủ sở hữu hợp pháp của phần đất này và có tên trên giấy chứng nhận quyền sử dụng đất và cha mẹ không thể thu hồi lại được.</ANSWER>
        </ANSWERS>
    </CONVERSATION>

    <CONVERSATION id='14' article="457">
        <QUESTIONS>
            <QUESTION>Cha mẹ cho con tài sản muốn đòi lại thì phải làm sao?</QUESTION>
        </QUESTIONS>
        <ANSWERS>
            <ANSWER>Để cha mẹ có thể đòi lại tài sản là quyền sử dụng đất đã sang tên cho con trước đó thì phải dựa vào ý chí của người con. Nếu người con đồng ý tặng cho lại quyền sử dụng đất này và sang tên cho cha mẹ thì cha mẹ mới có thể sở hữu phần đất này và thực hiện chia lại cho các người con thôi.</ANSWER>
        </ANSWERS>
    </CONVERSATION>

    <CONVERSATION id='15' article="557">
        <QUESTIONS>
            <QUESTION>Mất xe ở chung cư ai sẽ chịu trách nhiệm?</QUESTION>
        </QUESTIONS>
        <ANSWERS>
            <ANSWER clause='1'>Khi bị mất xe thì bên nhận giữ xe sẽ chịu trách nhiệm. Tức là bên mà Ban quản lý chung cư thuê để cung cấp dịch vụ trông giữ xe cho các cư dân.</ANSWER>
        </ANSWERS>
    </CONVERSATION>

    <CONVERSATION id='16' article="562">
        <QUESTIONS>
            <QUESTION>Hiện nay tôi đang có 1 tài sản nhà ở thế chấp vay vốn tại ngân hàng.&#xA;Tại thời điểm này tôi có thể thực hiện ủy quyền toàn phần cho một người khác (không phải cha mẹ, anh em ruột, người thân) thì có thể không?&#xA;Nếu được thì tôi có thể thực hiện việc ủy quyền này tại phòng công chứng hay tại địa điểm quy đình nào?</QUESTION>
        </QUESTIONS>
        <ANSWERS>
            <ANSWER>Đối với tài sản đang thế chấp thì bên thế chấp không được bán, trao đổi, tặng cho tài sản thế chấp trừ trường hợp được bên nhận thế chấp đồng ý. Việc ủy quyền để người khác thay mặt chủ sử dụng/chủ sở hữu tài sản làm các thủ tục để chuyển nhượng/bán tài sản theo quy định của pháp luật như bạn hỏi thì chưa có văn bản nào hạn chế thực hiện. Bạn vẫn có thể ủy quyền cho nười khác (không phải cha mẹ, anh em ruột, người thân) để thực hiện các nội dung đã nêu: trả nợ, nhận lại tài sản để thế chấp và sau khi hoàn thành việc trả nợ, xóa thế chấp thì được quyền chuyển nhượng, bán theo quy định của pháp luật. Với những nội dung ủy quyền này thì nhận ủy quyền chỉ được thay mặt bạn chuyển nhượng/bán tài sản đang thế chấp sau khi đã xóa đăng ký thế chấp tại cơ quan đăng ký giao dịch bảo đảm và phải thực hiện theo quy định của pháp luật. Như vậy, việc ủy quyền này là phù hợp với các quy định của pháp luật. Bạn có thể đến tổ chức công chứng để yêu cầu thực hiện hợp đồng ủy quyền này.</ANSWER>
        </ANSWERS>
    </CONVERSATION>

    <CONVERSATION id='17' article="468">
        <QUESTIONS>
            <QUESTION>Lãi suất cầm đồ theo quy định pháp luật hiện nay là bao nhiêu?</QUESTION>
        </QUESTIONS>
        <ANSWERS>
            <ANSWER>Lãi suất khi vay tiền sẽ do các bên tự nguyện thỏa thuận với nhau, nhưng không vượt quá 20% trên một năm của khoản tiền vay đó, trừ trường hợp luật có quy định khác.&#xA;- Nếu các bên tự thỏa thuận lãi suất, nhưng vượt quá lãi suất giới hạn mà luật quy định thì mức lãi suất vượt sẽ không có hiệu lực.&#xA;- Nếu các bên dù có thỏa thuận về trả lãi vay, tuy nhiên không có sự xác định rõ mức lãi suất là bao nhiêu phần trăm và có tranh chấp xảy ra, thì lãi suất sẽ xác định bằng 50% mức lãi suất luật quy định tại thời điểm trả nợ.</ANSWER>
        </ANSWERS>
    </CONVERSATION>

    <CONVERSATION id='18' article="471">
        <QUESTIONS>
            <QUESTION>Chơi hụi là gì?</QUESTION>
        </QUESTIONS>
        <ANSWERS>
            <ANSWER>Chơi hụi được giải thích như sau:&#xA;- Họ, hụi, biêu, phường (sau đây gọi chung là họ) là hình thức giao dịch về tài sản theo tập quán trên cơ sở thỏa thuận của một nhóm người tập hợp nhau lại cùng định ra số người, thời gian, số tiền hoặc tài sản khác, thể thức góp, lĩnh họ và quyền, nghĩa vụ của các thành viên.&#xA;- Dây họ là một họ hình thành trên cơ sở thỏa thuận cụ thể của những người tham gia họ về thời gian, phần họ, thể thức góp họ, lĩnh họ, quyền, nghĩa vụ của chủ họ (nếu có) và các thành viên.&#xA;- Thành viên là người tham gia dây họ, góp phần họ, được lĩnh họ và trả lãi (nếu có).&#xA;- Chủ họ là người tổ chức, quản lý dây họ, thu các phần họ và giao các phần họ đó cho thành viên được lĩnh họ trong mỗi kỳ mở họ cho tới khi kết thúc dây họ. Chủ họ có thể đồng thời là thành viên của dây họ.</ANSWER>
        </ANSWERS>
    </CONVERSATION>

    <CONVERSATION id='19' article="457">
        <QUESTIONS>
            <QUESTION>Hợp đồng tặng cho tài sản là gì?</QUESTION>
        </QUESTIONS>
        <ANSWERS>
            <ANSWER>Hợp đồng tặng cho tài sản là sự thỏa thuận giữa các bên, theo đó bên tặng cho giao tài sản của mình và chuyển quyền sở hữu cho bên được tặng cho mà không yêu cầu đền bù, bên được tặng cho đồng ý nhận.</ANSWER>
        </ANSWERS>
    </CONVERSATION>

    <CONVERSATION id='20' article="479">
        <QUESTIONS>
            <QUESTION>Bên thuê có phải bồi thường khi làm hư hỏng nhà trọ?</QUESTION>
        </QUESTIONS>
        <ANSWERS>
            <ANSWER>Nếu nhà hỏng do lỗi của bên thuê trong quá trình thuê không bảo quản nhà thuê thì ngoài việc phải sửa chữa, người thuê nhà còn phải bồi thường cho bên cho thuê nhà khi làm mất, hư hỏng tài sản thuê.</ANSWER>
        </ANSWERS>
    </CONVERSATION>
</CIVIL-CODE>