<CIVIL-CODE>
    <INFORMATION>
        <NAME>CIVIL CODE</NAME>
        <YEAR>2015</YEAR>
        <CHAPTER>25</CHAPTER>
        <LINK>https://thuvienphapluat.vn/van-ban/Quyen-dan-su/Bo-luat-dan-su-2015-296215.aspx</LINK>
    </INFORMATION>
    
    <CONVERSATION id='1' article="582">
        <QUESTIONS>
            <QUESTION>Nếu người nhận chuyển nhầm đã giao tiền cho bên thứ ba thì có đòi được không?</QUESTION>
        </QUESTIONS>
        <ANSWERS>
            <ANSWER>Nếu tiền đã được giao cho bên thứ ba thì chủ tài khoản có quyền yêu cầu bên thứ ba trả lại số tiền đã chuyển nhầm đó.</ANSWER>
        </ANSWERS>
    </CONVERSATION>



</CIVIL-CODE>